{"data":{"markdownRemark":{"frontmatter":{"title":"Education","subtitle":"My Qualification"}},"allMarkdownRemark":{"edges":[{"node":{"id":"04c542db-dbd1-58d2-8c33-cd0f47b51b77","html":"<p>Lorem ipsum dolor sit amet, consectetur adipiscing elit, sed do eiusmod tempor incididunt ut labore et dolore magna aliqua. Ut enim ad minim veniam, quis nostrud exercitation ullamco laborist.</p>","frontmatter":{"university":"Amazon Web Services","degree":"Developing on AWS","startDate":"Mar 2018","endDate":"Mar 2018"}}},{"node":{"id":"3faf29af-8203-58f4-a594-3454489321ff","html":"<p>Lorem ipsum dolor sit amet, consectetur adipiscing elit, sed do eiusmod tempor incididunt ut labore et dolore magna aliqua. Lorem ipsum dolor sit amet, consectetur adipiscing elit.</p>","frontmatter":{"university":"Ryerson University","degree":"B.Eng., Aerpsoace Engineering","startDate":"Sept 2008","endDate":"June 2015"}}}]}}}